{
  "id": "24_11_33",
  "source": "2024학년도 대학수학능력시험",
  "year": 2023,
  "month": 11,
  "exam_type_code": 1,
  "subject_code": "04",
  "type": "문학",
  "passage": "[32～34] 다음 글을 읽고 물음에 답하시오.\n\n(가)\n장풍에 돛을 달고 육선이 함께 떠나\n삼현과 군악 소리 해산을 진동하니\n물속의 어룡들이 응당히 놀라리라\n해구를 얼른 나서 오륙도를 뒤 지우고\n고국을 돌아보니 야색이 아득하여\n아무것도 아니 뵈고 연해 각진포에\n불빛 두어 점이 구름 밖에 뵐 만하다\n[A] 배 방에 누워 있어 내 신세를 생각하니\n가뜩이 심란한데 대풍이 일어나서\n태산 같은 성난 물결 천지에 자욱하니\n크나큰 만곡주가 나뭇잎 불리이듯\n하늘에 올랐다가 지함에 내려지니\n열두 발 쌍돛대는 차아처럼 굽어 있고\n쉰두 폭 초석 돛은 반달처럼 배불렀네\n(중략)\n[B] 날이 마침 극열하고 석양이 비치어서\n끓는 땅에 엎디어서 말씀을 여쭈오니\n속에서 불이 나고 관대에 땀이 배어\n물 흐르듯 하는지라 나라께서 보시고서\n너희 더위 어려우니 먼저 나가 쉬라시니\n곡배하고 사퇴하니 천은이 망극하다\n더위를 장히 먹어 막힐 듯하는지라\n사신들도 못 기다려 하처로 돌아오니\n[C] 누이도 반겨하고 딸은 기뻐 우는지라\n일가 친척들이 나와서 위문하네\n여드레 겨우 쉬어 공주로 내려가니\n처자식들 나를 보고 죽었던 이 고쳐 본 듯\n기쁘기 극한지라 어리석은 듯 앉았구나\n사당에 현알하고 옷도 벗고 편히 쉬니\n풍도의 험하던 일 저승 같고 꿈도 같다\n손주 안고 어르면서 한가히 누웠으니\n강호의 산인이요 성대의 일반이로다\n\n- 김인겸, 일동장유가 -\n\n(나)\n꼬아 자란 층석류*요 틀어 지은 고사매*라\n삼봉 괴석에 달린 솔이 늙었으니\n아마도 화암 풍경이 너뿐인가 하노라\n<제1수>\n막대 짚고 나와 거니니 양류풍 불어온다\n긴 파람 짧은 노래 뜻대로 소일하니\n어디서 초동과 목수(牧叟)는 웃고 가리키나니\n<제6수>\n맑은 물에 벼를 갈고 청산에 섶을 친 후\n서림 풍우에 소 먹여 돌아오니\n두어라 야인 생애도 자랑할 때 있으리라\n<제9수>\n\n- 유박, 화암구곡 -\n* 층석류 : 석류나무로 만든 분재.\n* 고사매 : 매화를 고목에 접붙인 분재.",
  "context_box": "",
  "question": "[A]～[C]에 대한 이해로 적절하지 않은 것은?",
  "options": [
    { "number": 1, "text": "[A]에서는 선상에서 불빛 두어 점에 의지해, 떠나온 곳을 가늠하는 행위를 통해 출항 후의 모습이 드러난다." },
    { "number": 2, "text": "[B]에서는 신하들의 고충을 헤아리는 임금의 배려에 감격한 마음이 드러난다." },
    { "number": 3, "text": "[C]에서는 갑작스러운 상황에 감정을 표현하지 못하고 무심하게 대응하는 가족들의 모습이 드러난다." },
    { "number": 4, "text": "[A]에서는 포구를 돌아보지만 보고 싶은 것이 보이지 않는 상황이, [B]에서는 격식을 갖추기 위해 뜨거운 땅에 엎드려 있는 일을 힘겨워하는 상황이 드러난다." },
    { "number": 5, "text": "[A]에서는 예기치 않게 맞닥뜨린 여정상의 위험이, [C]에서는 과거의 위험했던 경험에 대한 소회가 드러난다." }
  ],
  "answer_rate": 0,
  "difficulty": ""
}